Workbook

Sheet Asset Registry
A1: MACHFINISH FACILITY ASSET REGISTRY
A2: Equipment Tracking, Electrical Specs, & PM Schedule
A4: Asset ID | B4: Manufacturer | C4: Model No. | D4: Serial No. | E4: B.O.M. / Job / Order No. | F4: Asset Category | G4: Facility / Line | H4: Voltage / Power | I4: Full Load Current | J4: Operating Specs / Temp / Capacity | K4: Operational Status | L4: Criticality | M4: Install / Purchase Date | N4: Purchase Cost | O4: Last Service Date | P4: PM Frequency | Q4: Next Service Due
A5: EQ-101 | B5: Blue M Electric | C5: HS-362-1G | D5: HS-512 | E5: 78825 | F5: Industrial Oven | G5: Line 1 - Thermal | H5: 480V / 3PH / 60Hz | I5: 13.8A | J5: Up to 150°C | K5: Active | L5: High | M5: 2021-05-15 | N5: 14500 | O5: 2026-06-01 | P5: Quarterly | Q5: 2026-09-01
A6: EQ-102 | B6: Blue M Electric | C6: 166 BATCH OVEN | D6: DC-5634 | E6: 71082 | F6: Industrial Oven | G6: Line 1 - Thermal | H6: 480V / 3PH / 60Hz | I6: 17.0A | J6: 316°C / 600°F | K6: Active | L6: High | M6: 2021-08-10 | N6: 16200 | O6: 2026-06-01 | P6: Quarterly | Q6: 2026-09-01
A7: EQ-103 | B7: Blue M Electric | C7: HS-3802F | D7: HS-186 | E7: D1-00015 | F7: Industrial Oven | G7: Line 1 - Thermal | H7: 208-240V / 3PH / 60Hz | I7: 9.2A | J7: Up to 150°C / 302°F (Max 215°C) | K7: Active | L7: Medium | M7: 2022-02-18 | N7: 13800 | O7: 2026-06-01 | P7: Quarterly | Q7: 2026-09-01
A8: EQ-104 | B8: Thermal Product Solutions (TPS) | C8: DCSA - 246 - G - ST350 - HP | D8: 0701000117 - 01 | E8: Order: 41655 | F8: Industrial Oven | G8: Line 1 - Thermal | H8: 480V / 3PH / 60Hz | I8: 29.0A | J8: +316°C / (+600°F) | 21.0 KW | K8: Active | L8: High | M8: 2022-09-15 | N8: 21500 | O8: 2026-06-01 | P8: Quarterly | Q8: 2026-09-01
A9: EQ-105 | B9: Blue M Electric | C9: EM-366GX | D9: E3-4201 | F9: Industrial Oven | G9: Line 1 - Thermal | H9: 480V / 3PH / 60Hz | I9: 17.0A | J9: Up to 600°F | K9: Active | L9: High | M9: 2020-11-04 | N9: 15800 | O9: 2026-06-01 | P9: Quarterly | Q9: 2026-09-01
A10: EQ-106 | B10: The Grieve Corporation | C10: TA-500 | D10: 641468 | E10: Job: 63188A0501 | F10: Gas Industrial Oven | G10: Line 1 - Thermal | H10: 208V / 3PH / 60Hz | I10: 4.6A (3/4 HP Motor) | J10: Max 450°F | 100,000 BTU/HR | K10: Active | L10: High | M10: 2018-04-12 | N10: 24000 | O10: 2026-06-01 | P10: Quarterly | Q10: 2026-09-01
A11: EQ-107 | B11: JPW Industrial Ovens & Furnaces | C11: 496TULGEPR480V400BTUSR | D11: 002675 | F11: Industrial Oven | G11: Line 1 - Thermal | H11: 480V / 3PH / 60Hz | I11: 7.0A (Motor FLA: 3A) | J11: 500°F | K11: Active | L11: High | M11: 2019-12-01 | N11: 28500 | O11: 2026-06-01 | P11: Quarterly | Q11: 2026-09-01
A12: EQ-108 | B12: Process Technology, USA | C12: S4429-3-P1 | F12: Immersion Heater | G12: Process Tank / Wash Line | H12: 480V / 3PH / 50-60Hz | I12: 4.8A | J12: 4000 Watts (Liquid Heater) | K12: Active | L12: High | M12: 2023-04-10 | N12: 1850 | O12: 2026-06-15 | P12: Quarterly | Q12: 2026-09-15
A13: EQ-109 | B13: LS Electric | C13: LSLV0150S100-2EXNNS | D13: 550D713006F | E13: Panel B 2,4,6 | F13: Variable Frequency Drive (VFD) | G13: Main Control Panel | H13: 200-240V / 3PH / 50-60Hz | I13: Input: 66.7A | Output: 60.0A | J13: 22.9 kVA | IP66 | Preset: 36/46/56 Hz | K13: Active | L13: High | M13: 2024-01-15 | N13: 3200 | O13: 2026-05-20 | P13: Semi-Annual | Q13: 2026-11-20
A14: EQ-110 | B14: Eaton | C14: Heavy Duty Safety Switch | F14: Safety Switch / Disconnect | G14: Rooftop / Plant Power | H14: 600V AC / 250V DC / 60Hz | I14: 30A | J14: Heavy Duty Enclosed Switch | K14: Active | L14: Medium | M14: 2021-06-20 | N14: 450 | O14: 2026-01-10 | P14: Annual | Q14: 2027-01-10
A15: EQ-111 | B15: AeroCool / Essence | C15: Evaporative Air Cooler Unit | F15: HVAC / Evaporative Cooler | G15: Rooftop Unit | H15: 115V / 230V / 1PH | J15: Rooftop Industrial Cooler | K15: Active | L15: Medium | M15: 2020-05-18 | N15: 4500 | O15: 2026-04-01 | P15: Semi-Annual | Q15: 2026-10-01
A16: EQ-112 | B16: Spray Systems Inc. | C16: Finishing System | D16: 30-3086-03/12254B.1 | E16: 12254A / 12254B.2 | F16: Spray Booth / Finishing System | G16: Paint Line | J16: Complete Industrial Finishing System | K16: Active | L16: High | M16: 2019-09-10 | N16: 45000 | O16: 2026-06-01 | P16: Quarterly | Q16: 2026-09-01
A17: EQ-113 | B17: Greenheck | C17: 1B1-CA-5124-75-X | D17: 16098224 | E17: Mark: 11,520 CFM | F17: Industrial Exhaust Blower / Fan | G17: Rooftop Ventilation | J17: Max Class RPM: 2250 | 11,520 CFM | 1.75 SP | K17: Active | L17: High | M17: 2021-03-15 | N17: 6200 | O17: 2026-05-10 | P17: Semi-Annual | Q17: 2026-11-10
A18: EQ-114 | B18: Process Technology, USA | C18: C-DE404-P2 | D18: SN617384 | E18: Tag: H-001 / Cert: 1373894 | F18: Digital Temperature Controller | G18: Process Line Control Panel | H18: 480V / 3PH / 50-60Hz | I18: 40.0A (Max FLA) | J18: Digital Temp Controller (DE20 Series) | K18: Active | L18: High | M18: 2022-11-05 | N18: 850 | O18: 2026-06-01 | P18: Annual | Q18: 2027-06-01
A19: EQ-115 | B19: New Holland | C19: Model K-24 | F19: Industrial Dryer (W/ Elect Heater) | G19: Parts Drying Line | H19: 440V / 3PH / 60Hz | I19: 9.5A (FLA) | MCA: 11.9A | J19: 4000W Heat Element (460V) | Fuse: FRS 12 | K19: Active | L19: High | M19: 2020-08-22 | N19: 12500 | O19: 2026-03-15 | P19: Quarterly | Q19: 2026-06-15
A20: EQ-116 | B20: TRU - AIRE Industries, Inc. | C20: 900 Series Diffuser / Grille | E20: L.A. CITY RR 7837 | F20: HVAC Air Distribution / Ductwork | G20: Building HVAC | J20: UL 181 Compliant Ductwork / Grille | K20: Active | L20: Low | M20: 2018-06-10 | N20: 350 | O20: 2025-10-01 | P20: Annual | Q20: 2026-10-01
A21: EQ-117 | B21: Process Technology, USA | C21: 3S9423M-3-P2 | E21: Listed E73679 | F21: Immersion Type Liquid Heater | G21: Process Tank / Wash Line | H21: 480V / 3PH / 50-60Hz | I21: 10.8A | J21: 9000 Watts (Liquid Heater) | K21: Active | L21: High | M21: 2023-05-10 | N21: 2200 | O21: 2026-06-15 | P21: Quarterly | Q21: 2026-09-15
A22: EQ-118 | B22: Bison / AMETEK (Lamb) | C22: 116196-00 | D22: FF6 | E22: 09/02/25 | F22: Blower / Vacuum Motor | G22: Exhaust / Dust Collection System | H22: 120V / 1PH / 60Hz | J22: Blower Motor Assembly (UL E47185) | K22: Active | L22: Medium | M22: 2022-04-18 | N22: 650 | O22: 2026-05-01 | P22: Semi-Annual | Q22: 2026-11-01
A23: EQ-121 | B23: International Comfort Products (ICP) | C23: HHP024AKC3 | D23: E043050940 | E23: Part: 328858-4144 | F23: HVAC Heat Pump / Condenser | G23: Rooftop Unit | H23: 208/230V / 1PH / 60Hz | I23: 16.3A (MCA) | Max Fuse: 25A | J23: Compressor: 11.9A (RLA) | Fan: 1.4A | R-22 | K23: Active | L23: High | M23: 2021-04-15 | N23: 5800 | O23: 2026-05-01 | P23: Semi-Annual | Q23: 2026-11-01
A24: EQ-122 | B24: Empire Abrasive Equipment Co. | C24: PF-3648 | D24: 7662 | E24: PRO - FINISH | F24: Abrasive Blasting Cabinet | G24: Surface Prep / Finishing Bay | H24: 120V / 1PH / 60Hz | J24: Heavy-Duty Abrasive Blast Cabinet | K24: Active | L24: Medium | M24: 2020-09-12 | N24: 8900 | O24: 2026-03-20 | P24: Quarterly | Q24: 2026-06-20
A25: EQ-123 | B25: GE Appliances | C25: GIE16GSHCRSS | D25: TG792984 | E25: 245D1017P025 | F25: Breakroom Refrigerator / Freezer | G25: Facility Breakroom | H25: 110-127V / 1PH / 60Hz | I25: 6.5A | J25: 100V 50Hz Opt | R134a (4.375 oz) | K25: Active | L25: Low | M25: 2022-10-05 | N25: 850 | O25: 2025-10-15 | P25: Annual | Q25: 2026-10-15
A26: EQ-124 | B26: KAESER KOMPRESSOREN | C26: SFC 75S | D26: 1012 - 7120537 | E26: Material: 101356.2 | F26: Rotary Screw Air Compressor | G26: Compressor Room | H26: 460Y/266V / 3PH / 60Hz | I26: 137A (Drive Motor: 152A) | J26: 100 HP | 125 psig | 440 cfm | Fuse: 200A Class AJT | K26: Active | L26: High | M26: 2019-07-01 | N26: 38500 | O26: 2026-06-15 | P26: Monthly | Q26: 2026-07-15
A27: EQ-125 | B27: Nidec Motor Corporation (U.S. MOTORS) | C27: HE22 (Catalog: D3P2D) | D27: B 05 7736780 - 0066 M 0014 | E27: Frame: 182T | F27: 3-Phase AC Electric Motor | G27: Plant Maintenance / Equipment Drive | H27: 208-230/460V / 3PH / 60Hz | I27: 8.30-7.80 / 3.90A | J27: 3.0 HP | 1770 RPM | SF 1.15 | Inverter Duty 20:1 VT & 4:1 CT | K27: Active | L27: Medium | M27: 2022-03-10 | N27: 1250 | O27: 2026-04-01 | P27: Semi-Annual | Q27: 2026-10-01
A28: Total Valuation | N28: =SUM(N5:N27) -> 267350

Sheet Maintenance Overview
A1: MACHFINISH MAINTENANCE PROGRAM OVERVIEW
A2: Executive Summary, Criticality Matrix, Location Breakdown & PM Schedules
A4: 1. Key Metrics & Portfolio Summary
A5: Metric Description | B5: Value
A6: Total Active Equipment Units | B6: =COUNTA('Asset Registry'!A5:A27) -> 23
A7: Total Asset Portfolio Valuation | B7: =SUM('Asset Registry'!N5:N27) -> 267350
A8: High Criticality Assets (65.2%) | B8: =COUNTIF('Asset Registry'!L5:L27, "High") -> 15
A9: Medium Criticality Assets (26.1%) | B9: =COUNTIF('Asset Registry'!L5:L27, "Medium") -> 6
A10: Low Criticality Assets (8.7%) | B10: =COUNTIF('Asset Registry'!L5:L27, "Low") -> 2
A12: 2. Preventive Maintenance Schedule Matrix
A13: PM Frequency | B13: Unit Count | C13: Associated Asset IDs | D13: Maintenance Scope & Key Focus
A14: Monthly | B14: =COUNTIF('Asset Registry'!P5:P27, "Monthly") -> 1 | C14: EQ-124 | D14: Kaeser Screw Compressor: Check fluid levels, clean air filters, test automatic condensate drains, inspect belt drive, monitor pressure/temp.
A15: Quarterly | B15: =COUNTIF('Asset Registry'!P5:P27, "Quarterly") -> 12 | C15: EQ-101 to 108, EQ-112, EQ-115, EQ-117, EQ-122 | D15: Ovens, Heaters, Finishing & Blasting: Thermocouple calibration, heating element amp draw, exhaust draft check, door seal gaskets, booth filters.
A16: Semi-Annual | B16: =COUNTIF('Asset Registry'!P5:P27, "Semi-Annual") -> 6 | C16: EQ-109, EQ-111, EQ-113, EQ-118, EQ-121, EQ-125 | D16: Motors, VFDs, Blowers & HVAC: Terminal torque checks, thermal imaging, shaft alignment, bearing lubrication (182T frame), condenser cleaning.
A17: Annual | B17: =COUNTIF('Asset Registry'!P5:P27, "Annual") -> 4 | C17: EQ-110, EQ-114, EQ-116, EQ-123 | D17: Safety, Controls & Facilities: Disconnect contact inspection, digital controller recalibration, ductwork airflow balance check, containment seals.
A20: 3. Facility Line & Asset Location Breakdown
A21: Facility / Line | B21: Asset Count | C21: Line Asset Valuation | D21: Primary Equipment Types
A22: Line 1 - Thermal | B22: 7 | C22: 134300 | D22: Electric & Gas Ovens (EQ-101 to EQ-107)
A23: Paint Line | B23: 1 | C23: 45000 | D23: Spray Booth / Finishing System (EQ-112)
A24: Compressor Room | B24: 1 | C24: 38500 | D24: Kaeser 100 HP Screw Compressor (EQ-124)
A25: Parts Drying Line | B25: 1 | C25: 12500 | D25: Industrial Dryer with Electric Heat (EQ-115)
A26: Rooftop Units & Ventilation | B26: 3 | C26: 16500 | D26: Heat Pump, Blower Fan & Evaporative Cooler (EQ-111, 113, 121)
A27: Surface Prep / Finishing Bay | B27: 1 | C27: 8900 | D27: Abrasive Blasting Cabinet (EQ-122)
A28: Process Tank / Wash Line | B28: 2 | C28: 4050 | D28: Immersion Liquid Heaters (EQ-108, 117)
A29: Control Panels & Power Distribution | B29: 3 | C29: 4500 | D29: LS VFD (EQ-109), Temp Controller (EQ-114), Safety Switch (EQ-110)
A30: Plant Maintenance Drive & Support | B30: 4 | C30: 3100 | D30: Electric Motor (EQ-125), Dust Vacuum (EQ-118), Ductwork, Breakroom
A31: TOTALS | B31: =SUM(B22:B30) -> 23 | C31: =SUM(C22:C30) -> 267350

Sheet PM Schedule
A1: MACHFINISH PREVENTIVE MAINTENANCE (PM) SCHEDULE
A2: Master Maintenance Execution Plan, Recurring Tasks, and Work Order Calendar
A4: Asset ID | B4: Equipment Description | C4: Facility / Line | D4: Criticality | E4: PM Frequency | F4: Last Service Date | G4: Next Service Due | H4: Assigned Task / Service Standard | I4: Est. Labor (Hrs) | J4: Required Parts / Consumables | K4: Completion Status
A5: EQ-124 | B5: KAESER Rotary Screw Air Compressor (SFC 75S) | C5: Compressor Room | D5: High | E5: Monthly | F5: 2026-06-15 | G5: =EDATE(F5, 1) -> 46218 | H5: Inspect oil level/color, test automatic condensate drains, clean intake air filter element, inspect belt tension, check operating pressure & temp. | I5: 1.5 | J5: Air Filter Element (101356.2), Compressor Synthetic Fluid | K5: Scheduled
A6: EQ-101 | B6: Blue M Industrial Oven (HS-362-1G) | C6: Line 1 - Thermal | D6: High | E6: Quarterly | F6: 2026-06-01 | G6: =EDATE(F6, 3) -> 46266 | H6: Calibrate temperature controller, inspect heating elements & contactors, clean blower wheel, inspect door silicone seals/gaskets. | I6: 2 | J6: Door Gasket Strip, Contactor Kit | K6: Scheduled
A7: EQ-102 | B7: Blue M Batch Oven (166 BATCH) | C7: Line 1 - Thermal | D7: High | E7: Quarterly | F7: 2026-06-01 | G7: =EDATE(F7, 3) -> 46266 | H7: High-temp thermal element resistance test, verify safety over-temp cutoff, lubricate blower motor bearings, check door latch alignment. | I7: 2 | J7: Heating Element Spares, High-Temp Sealant | K7: Scheduled
A8: EQ-103 | B8: Blue M Industrial Oven (HS-3802F) | C8: Line 1 - Thermal | D8: Medium | E8: Quarterly | F8: 2026-06-01 | G8: =EDATE(F8, 3) -> 46266 | H8: Inspect heating coil connections, calibrate digital thermocouple, clean interior chamber, check exhaust damper position. | I8: 1.5 | J8: Thermocouple Probe (Type J/K) | K8: Scheduled
A9: EQ-104 | B9: TPS Industrial Oven (DCSA-246) | C9: Line 1 - Thermal | D9: High | E9: Quarterly | F9: 2026-06-01 | G9: =EDATE(F9, 3) -> 46266 | H9: Inspect 21.0 kW heating bank terminals, verify air circulation switch operation, clean recirculation fan, inspect insulation seals. | I9: 2.5 | J9: 21kW Contactor Set, Door Seal Gasket | K9: Scheduled
A10: EQ-105 | B10: Blue M Industrial Oven (EM-366GX) | C10: Line 1 - Thermal | D10: High | E10: Quarterly | F10: 2026-06-01 | G10: =EDATE(F10, 3) -> 46266 | H10: Test high-limit control switch, inspect electrical heating elements, clean ventilation duct connections, check door hinges/latches. | I10: 2 | J10: High-Limit Switch Relay | K10: Scheduled
A11: EQ-106 | B11: The Grieve Corp Gas Oven (TA-500) | C11: Line 1 - Thermal | D11: High | E11: Quarterly | F11: 2026-06-01 | G11: =EDATE(F11, 3) -> 46266 | H11: Inspect 100k BTU gas burner assembly, check spark igniter & flame rod, test gas safety shut-off valve, lubricate 3/4 HP blower motor. | I11: 2.5 | J11: Igniter Electrode, Flame Sensor Rod | K11: Scheduled
A12: EQ-107 | B12: JPW Industrial Oven (496TULGEPR) | C12: Line 1 - Thermal | D12: High | E12: Quarterly | F12: 2026-06-01 | G12: =EDATE(F12, 3) -> 46266 | H12: Check heater coil current draw (FLA 7.0A), test safety interlocks, clean recirculation fan blades, inspect cabinet insulation. | I12: 2 | J12: Safety Interlock Switch | K12: Scheduled
A13: EQ-108 | B13: Process Tech Immersion Heater (S4429) | C13: Process Tank / Wash Line | D13: High | E13: Quarterly | F13: 2026-06-15 | G13: =EDATE(F13, 3) -> 46280 | H13: Inspect PFA fluoropolymer coating for erosion, check 4kW heating element impedance, verify liquid level cutoff sensor, clean tank scale build-up. | I13: 1.5 | J13: Liquid Level Sensor Probe | K13: Scheduled
A14: EQ-112 | B14: Spray Systems Finishing System | C14: Paint Line | D14: High | E14: Quarterly | F14: 2026-06-01 | G14: =EDATE(F14, 3) -> 46266 | H14: Replace exhaust arrestor filter media, check duct static pressure, inspect fluid spray pumps & lines, clean exhaust fan blades. | I14: 3 | J14: Paint Arrestor Filter Media, Pump Seal Kit | K14: Scheduled
A15: EQ-115 | B15: New Holland Industrial Dryer (K-24) | C15: Parts Drying Line | D15: High | E15: Quarterly | F15: 2026-03-15 | G15: =EDATE(F15, 3) -> 46188 | H15: Inspect 4000W electric heating elements, test lid safety interlock switch, check motor drive V-belt tension, grease basket spindle bearings. | I15: 1.5 | J15: Drive Belt, FRS 12 Fuses | K15: Scheduled
A16: EQ-117 | B16: Process Tech Immersion Liquid Heater | C16: Process Tank / Wash Line | D16: High | E16: Quarterly | F16: 2026-06-15 | G16: =EDATE(F16, 3) -> 46280 | H16: Inspect 9000W heating element jacket, verify terminal box water tightness, test ground fault circuit, clean tank sludge build-up. | I16: 1.5 | J16: Terminal Gasket Set | K16: Scheduled
A17: EQ-122 | B17: Empire Abrasive Blast Cabinet (PF-3648) | C17: Surface Prep / Finishing Bay | D17: Medium | E17: Quarterly | F17: 2026-03-20 | G17: =EDATE(F17, 3) -> 46193 | H17: Inspect blast nozzle & air mixing valve wear, replace dust collector filter cartridge, check door window protective film, inspect blast gloves. | I17: 2 | J17: Blast Nozzle (Boron Carbide), Filter Cartridge | K17: Scheduled
A18: EQ-109 | B18: LS Electric VFD Panel (LSLV0150S100) | C18: Main Control Panel | D18: High | E18: Semi-Annual | F18: 2026-05-20 | G18: =EDATE(F18, 6) -> 46346 | H18: Clean heat sink cooling fan & enclosure air intake, retighten power terminal screws to spec, check DC bus capacitor voltage, review fault log. | I18: 1.5 | J18: Panel Intake Dust Filter | K18: Scheduled
A19: EQ-111 | B19: AeroCool Evaporative Air Cooler Unit | C19: Rooftop Unit | D19: Medium | E19: Semi-Annual | F19: 2026-04-01 | G19: =EDATE(F19, 6) -> 46296 | H19: Inspect water distribution lines & pads, flush sump basin, lubricate blower bearings, check belt tension & pulley alignment. | I19: 2 | J19: Cooler Media Pads, Drive Belt | K19: Scheduled
A20: EQ-113 | B20: Greenheck Exhaust Blower (1B1-CA) | C20: Rooftop Ventilation | D20: High | E20: Semi-Annual | F20: 2026-05-10 | G20: =EDATE(F20, 6) -> 46336 | H20: Inspect 11,520 CFM blower wheel balance, grease shaft bearings, check V-belt tension/wear, inspect flexible duct connections. | I20: 1.5 | J20: V-Belt, Bearing Grease (Lithium Complex) | K20: Scheduled
A21: EQ-118 | B21: Bison / AMETEK Blower Motor (116196) | C21: Exhaust / Dust Collection System | D21: Medium | E21: Semi-Annual | F21: 2026-05-01 | G21: =EDATE(F21, 6) -> 46327 | H21: Inspect motor carbon brushes for wear, clean housing cooling slots, test vacuum suction performance, inspect wiring leads. | I21: 1 | J21: Replacement Carbon Brushes | K21: Scheduled
A22: EQ-121 | B22: ICP Rooftop Heat Pump / Condenser | C22: Rooftop Unit | D22: High | E22: Semi-Annual | F22: 2026-05-01 | G22: =EDATE(F22, 6) -> 46327 | H22: Clean condenser coils, check R-22 operating pressures, measure compressor FLA (11.9A), inspect fan motor capacitor, flush condensate drain. | I22: 2 | J22: Air Filters, Compressor Capacitor | K22: Scheduled
A23: EQ-125 | B23: Nidec 3-Phase Electric Motor (182T Frame) | C23: Plant Maintenance / Equipment Drive | D23: Medium | E23: Semi-Annual | F23: 2026-04-01 | G23: =EDATE(F23, 6) -> 46296 | H23: Grease motor bearings (6206-2Z), check shaft alignment & mounting bolts, measure winding insulation resistance (Megger test), check terminal box connections. | I23: 1 | J23: Polyurea Bearing Grease | K23: Scheduled
A24: EQ-110 | B24: Eaton Heavy Duty Safety Switch (30A) | C24: Rooftop / Plant Power | D24: Medium | E24: Annual | F24: 2026-01-10 | G24: =EDATE(F24, 12) -> 46397 | H24: Perform infrared thermography scan under load, inspect fuse clips & contact blade corrosion, test mechanical door interlock. | I24: 1 | J24: 30A Fuses, Contact Cleaner | K24: Scheduled
A25: EQ-114 | B25: Process Tech Digital Temp Controller | C25: Process Line Control Panel | D25: High | E25: Annual | F25: 2026-06-01 | G25: =EDATE(F25, 12) -> 46539 | H25: Calibrate digital temperature display against reference standard, check solid-state relay (SSR) output, inspect control wiring terminals. | I25: 1 | J25: Calibration Ref Probe | K25: Scheduled
A26: EQ-116 | B26: TRU-AIRE HVAC Ductwork / Diffuser Grille | C26: Building HVAC | D26: Low | E26: Annual | F26: 2025-10-01 | G26: =EDATE(F26, 12) -> 46296 | H26: Inspect duct connections for air leaks, clean diffusers & supply grilles, check volume damper control levers. | I26: 0.5 | J26: Duct Sealing Tape, Cleaning Solution | K26: Scheduled
A27: EQ-123 | B27: GE Breakroom Refrigerator / Freezer | C27: Facility Breakroom | D27: Low | E27: Annual | F27: 2025-10-15 | G27: =EDATE(F27, 12) -> 46310 | H27: Clean condenser coils & compressor compartment, inspect magnetic door gaskets, verify temperature settings (37°F / 0°F), clean drain line. | I27: 0.5 | J27: Coil Brush, Door Gasket Spray | K27: Scheduled
A28: Total PM Labor Hours per Cycle | I28: =SUM(I5:I27) -> 37.5
